gnpy_api-0.1.2.dist-info/licenses/AUTHORS
gnpy_api-0.1.2.dist-info/licenses/LICENSE
gnpyapi/__init__.py
gnpyapi/core/__init__.py
gnpyapi/core/exception/__init__.py
gnpyapi/core/exception/config_error.py
gnpyapi/core/exception/equipment_error.py
gnpyapi/core/exception/exception_handler.py
gnpyapi/core/exception/path_computation_error.py
gnpyapi/core/exception/topology_error.py
gnpyapi/core/model/__init__.py
gnpyapi/core/model/error.py
gnpyapi/core/model/result.py
gnpyapi/core/route/__init__.py
gnpyapi/core/route/path_request_route.py
gnpyapi/core/route/status_route.py
gnpyapi/core/service/__init__.py
gnpyapi/core/service/config_service.py
gnpyapi/core/service/equipment_service.py
gnpyapi/core/service/path_request_service.py
gnpyapi/core/service/topology_service.py
gnpyapi/exampledata/planning_demand_example.json
gnpyapi/tools/__init__.py
gnpyapi/yang/gnpy-api@2021-01-06.yang
gnpyapi/yang/gnpy-eqpt-config@2020-10-22.yang
gnpyapi/yang/gnpy-eqpt-config@2025-01-20.yang
gnpyapi/yang/gnpy-network-topology@2020-10-22.yang
gnpyapi/yang/gnpy-network-topology@2025-01-20.yang
gnpyapi/yang/gnpy-path-computation-simplified@2020-10-22.yang
gnpyapi/yang/gnpy-path-computation@2025-01-21.yang
gnpyapi/yang/ietf-layer0-types@2024-03-04.yang
gnpyapi/yang/ietf-optical-impairment-topology@2024-05-21.yang
gnpyapi/yang/ietf-routing-types@2017-12-04.yang
gnpyapi/yang/ietf-te-topology@2020-08-06.yang
gnpyapi/yang/ietf-te-types@2022-10-21.yang
gnpy_api-0.1.2.dist-info/METADATA
gnpy_api-0.1.2.dist-info/WHEEL
gnpy_api-0.1.2.dist-info/pbr.json
gnpy_api-0.1.2.dist-info/top_level.txt
gnpy_api-0.1.2.dist-info/RECORD
